setup.py
imlp/__init__.py
imlp/connection.py
imlp/dataset.py
imlp/ihdfs.py
imlp/iminio.py
imlp/imysql.py
imlp/model.py
imlp/test.py
imlp/utils.py
imlp.egg-info/PKG-INFO
imlp.egg-info/SOURCES.txt
imlp.egg-info/dependency_links.txt
imlp.egg-info/requires.txt
imlp.egg-info/top_level.txt