Metadata-Version: 1.0
Name: imlp
Version: 1.0.1
Summary: IMLP SDK
Home-page: UNKNOWN
Author: bruce
Author-email: zhaozhenxiu@inspur.com
License: UNKNOWN
Platform: UNKNOWN
